pydng/__init__.py
pydng/pydng.py
tests/__init__.py
tests/test_pydng.py
tests/integration/__init__.py
tests/integration/test_pydng.py
pydng-1.1.2.dist-info/LICENSE
pydng-1.1.2.dist-info/METADATA
pydng-1.1.2.dist-info/WHEEL
pydng-1.1.2.dist-info/entry_points.txt
pydng-1.1.2.dist-info/top_level.txt
pydng-1.1.2.dist-info/RECORD
