Metadata-Version: 2.1
Name: pydng
Version: 1.1.2
Summary: Docker random name generator ported to Python. Just because.
Home-page: https://github.com/irlrobot/pydng
Author: Josh Campbell
Author-email: josh@userdel.com
License: UNKNOWN
Platform: UNKNOWN
Classifier: Programming Language :: Python :: 3
Classifier: License :: OSI Approved :: MIT License
Classifier: Operating System :: OS Independent
